[
  {
    "name": "@babel/runtime",
    "version": "7.29.2",
    "license": "MIT",
    "repository": "https://github.com/babel/babel"
  },
  {
    "name": "@popperjs/core",
    "version": "2.11.5",
    "license": "MIT",
    "repository": "https://github.com/popperjs/popper-core"
  },
  {
    "name": "@types/raf",
    "version": "3.4.0",
    "license": "MIT",
    "repository": "https://github.com/DefinitelyTyped/DefinitelyTyped"
  },
  {
    "name": "atob",
    "version": "2.1.2",
    "license": "(MIT OR Apache-2.0)",
    "repository": "git://git.coolaj86.com/coolaj86/atob.js"
  },
  {
    "name": "base64-arraybuffer",
    "version": "1.0.2",
    "license": "MIT",
    "repository": "https://github.com/niklasvh/base64-arraybuffer"
  },
  {
    "name": "blob-polyfill",
    "version": "6.0.20211015",
    "license": "MIT",
    "repository": "https://github.com/bjornstar/blob-polyfill"
  },
  {
    "name": "bootstrap",
    "version": "5.1.3",
    "license": "MIT",
    "repository": "https://github.com/twbs/bootstrap"
  },
  {
    "name": "bootstrap-icons",
    "version": "1.8.3",
    "license": "MIT",
    "repository": "https://github.com/twbs/icons"
  },
  {
    "name": "btoa",
    "version": "1.2.1",
    "license": "(MIT OR Apache-2.0)",
    "repository": "git://git.coolaj86.com/coolaj86/btoa.js"
  },
  {
    "name": "canvg",
    "version": "3.0.10",
    "license": "MIT",
    "repository": "https://github.com/canvg/canvg"
  },
  {
    "name": "core-js",
    "version": "3.25.5",
    "license": "MIT",
    "repository": "https://github.com/zloirock/core-js"
  },
  {
    "name": "cross-blob",
    "version": "3.0.1",
    "license": "MIT",
    "repository": "https://github.com/Richienb/cross-blob"
  },
  {
    "name": "css-line-break",
    "version": "2.1.0",
    "license": "MIT",
    "repository": "https://github.com/niklasvh/css-line-break"
  },
  {
    "name": "debug",
    "version": "2.6.9",
    "license": "MIT",
    "repository": "https://github.com/visionmedia/debug"
  },
  {
    "name": "dexie",
    "version": "3.2.2",
    "license": "Apache-2.0",
    "repository": "https://github.com/dfahlander/Dexie.js"
  },
  {
    "name": "dexie-export-import",
    "version": "4.1.4",
    "license": "Apache-2.0",
    "repository": "https://github.com/dexie/Dexie.js"
  },
  {
    "name": "dompurify",
    "version": "2.4.0",
    "license": "(MPL-2.0 OR Apache-2.0)",
    "repository": "https://github.com/cure53/DOMPurify"
  },
  {
    "name": "electron-is-dev",
    "version": "2.0.0",
    "license": "MIT",
    "repository": "https://github.com/sindresorhus/electron-is-dev"
  },
  {
    "name": "electron-squirrel-startup",
    "version": "1.0.0",
    "license": "Apache-2.0",
    "repository": "https://github.com/mongodb-js/electron-squirrel-startup"
  },
  {
    "name": "fetch-blob",
    "version": "3.2.0",
    "license": "MIT",
    "repository": "https://github.com/node-fetch/fetch-blob"
  },
  {
    "name": "fflate",
    "version": "0.4.8",
    "license": "MIT",
    "repository": "https://github.com/101arrowz/fflate"
  },
  {
    "name": "html2canvas",
    "version": "1.4.1",
    "license": "MIT",
    "repository": "https://github.com/niklasvh/html2canvas"
  },
  {
    "name": "jquery",
    "version": "3.6.0",
    "license": "MIT",
    "repository": "https://github.com/jquery/jquery"
  },
  {
    "name": "jspdf",
    "version": "2.5.1",
    "license": "MIT",
    "repository": "https://github.com/MrRio/jsPDF"
  },
  {
    "name": "mktemp",
    "version": "1.0.0",
    "license": "MIT",
    "repository": "https://github.com/sasaplus1/mktemp"
  },
  {
    "name": "ms",
    "version": "2.0.0",
    "license": "MIT",
    "repository": "https://github.com/zeit/ms"
  },
  {
    "name": "node-domexception",
    "version": "1.0.0",
    "license": "MIT",
    "repository": "https://github.com/jimmywarting/node-domexception"
  },
  {
    "name": "performance-now",
    "version": "2.1.0",
    "license": "MIT",
    "repository": "https://github.com/braveg1rl/performance-now"
  },
  {
    "name": "raf",
    "version": "3.4.1",
    "license": "MIT",
    "repository": "https://github.com/chrisdickinson/raf"
  },
  {
    "name": "regenerator-runtime",
    "version": "0.13.9",
    "license": "MIT",
    "repository": "https://github.com/facebook/regenerator/tree/master/packages/runtime"
  },
  {
    "name": "rgbcolor",
    "version": "1.0.1",
    "license": "MIT*",
    "repository": "https://github.com/yetzt/node-rgbcolor"
  },
  {
    "name": "stackblur-canvas",
    "version": "2.5.0",
    "license": "MIT",
    "repository": "https://github.com/flozz/StackBlur"
  },
  {
    "name": "strftime",
    "version": "0.10.3",
    "license": "MIT",
    "repository": "https://github.com/samsonjs/strftime"
  },
  {
    "name": "svg-pathdata",
    "version": "6.0.3",
    "license": "MIT",
    "repository": "https://github.com/nfroidure/svg-pathdata"
  },
  {
    "name": "text-segmentation",
    "version": "1.0.3",
    "license": "MIT",
    "repository": "https://github.com/niklasvh/text-segmentation"
  },
  {
    "name": "utrie",
    "version": "1.0.2",
    "license": "MIT",
    "repository": "https://github.com/niklasvh/utrie"
  },
  {
    "name": "web-streams-polyfill",
    "version": "3.2.1",
    "license": "MIT",
    "repository": "https://github.com/MattiasBuelens/web-streams-polyfill"
  }
]
